{
    "Culture": "en",
    "Name": "English",
    "Country": null,
    "Strings":
    {
        "mainmenu_intro": "...",
        "mainmenu_poweredBy": "Powered by §[255,110,35]MonoGame§",
        "mainmenu_addressQuery": "Server Address: ",
        "mainmenu_awaitingResponse_x": "Awaiting Response ({0})...",
        "mainmenu_resolvingAddress_x": "Resolving Address ({0})...",
        "mainmenu_invalidAddress": "Invalid Address",
        "mainmenu_connectingTo_x": "Connecting to '{0}'",
        "mainmenu_connectionSuccessful": "Connection Successful",
        "generic_resolvingAddress": "Resolving Address...",
        "generic_connectionTimeout": "Connection Timed Out",
        "generic_loading": "Loading"
    }
}
